LICENSE
README.md
setup.py
starstar/__init__.py
starstar/__version__.py
starstar/argparse.py
starstar/core.py
starstar/dcp_nesteddoc.py
starstar/debug.py
starstar/defaults.py
starstar/docstr.py
starstar/parse.py
starstar/unpack.py
starstar.egg-info/PKG-INFO
starstar.egg-info/SOURCES.txt
starstar.egg-info/dependency_links.txt
starstar.egg-info/requires.txt
starstar.egg-info/top_level.txt