Metadata-Version: 2.1
Name: starstar
Version: 0.6.1
Summary: Keyword argument tracing !!
Home-page: https://github.com/beasteers/starstar
Author: Bea Steers
Author-email: bea.steers@gmail.com
License: MIT License
Keywords: keyword kwargs kw star function arguments signature wrap trace
Provides-Extra: test
Provides-Extra: doc
License-File: LICENSE
